CandleView/CandleView.py
CandleView/__init__.py
CandleView-0.0.4.dist-info/LICENSE
CandleView-0.0.4.dist-info/METADATA
CandleView-0.0.4.dist-info/WHEEL
CandleView-0.0.4.dist-info/top_level.txt
CandleView-0.0.4.dist-info/RECORD
